{
  "run_id": "20260505_004647",
  "source_image": "data/sample_images/old-19th-century-gold-coins-collection-vintage-engraved-illustration.webp",
  "timestamp": "2026-05-05T00:46:47.043546",
  "summary": {
    "total_count": 86,
    "total_detected": 86,
    "breakdown": [
      {
        "category": "Small",
        "count": 27
      },
      {
        "category": "Medium",
        "count": 23
      },
      {
        "category": "Large",
        "count": 36
      }
    ],
    "category_counts": {
      "Large": 36,
      "Medium": 23,
      "Small": 27
    },
    "avg_confidence": 0.7023255813953488,
    "low_confidence_count": 0
  },
  "coins": [
    {
      "coin_index": 0,
      "category": "Large",
      "is_coin": true,
      "confidence": 0.85,
      "color_group": "BICOLOR",
      "circle": {
        "x": 255,
        "y": 281,
        "r": 199
      },
      "reasoning": [
        "Good color saturation",
        "Typical coin surface texture",
        "Matches BICOLOR group"
      ]
    },
    {
      "coin_index": 1,
      "category": "Large",
      "is_coin": true,
      "confidence": 0.85,
      "color_group": "BICOLOR",
      "circle": {
        "x": 425,
        "y": 321,
        "r": 147
      },
      "reasoning": [
        "Good color saturation",
        "Typical coin surface texture",
        "Matches BICOLOR group"
      ]
    },
    {
      "coin_index": 2,
      "category": "Large",
      "is_coin": true,
      "confidence": 0.85,
      "color_group": "BICOLOR",
      "circle": {
        "x": 457,
        "y": 192,
        "r": 116
      },
      "reasoning": [
        "Good color saturation",
        "Typical coin surface texture",
        "Matches BICOLOR group"
      ]
    },
    {
      "coin_index": 3,
      "category": "Large",
      "is_coin": true,
      "confidence": 0.85,
      "color_group": "BICOLOR",
      "circle": {
        "x": 145,
        "y": 328,
        "r": 114
      },
      "reasoning": [
        "Good color saturation",
        "Typical coin surface texture",
        "Matches BICOLOR group"
      ]
    },
    {
      "coin_index": 4,
      "category": "Large",
      "is_coin": true,
      "confidence": 0.85,
      "color_group": "BICOLOR",
      "circle": {
        "x": 298,
        "y": 149,
        "r": 112
      },
      "reasoning": [
        "Good color saturation",
        "Typical coin surface texture",
        "Matches BICOLOR group"
      ]
    },
    {
      "coin_index": 5,
      "category": "Large",
      "is_coin": true,
      "confidence": 0.85,
      "color_group": "BICOLOR",
      "circle": {
        "x": 147,
        "y": 204,
        "r": 110
      },
      "reasoning": [
        "Good color saturation",
        "Typical coin surface texture",
        "Matches BICOLOR group"
      ]
    },
    {
      "coin_index": 6,
      "category": "Large",
      "is_coin": true,
      "confidence": 0.85,
      "color_group": "BICOLOR",
      "circle": {
        "x": 292,
        "y": 412,
        "r": 105
      },
      "reasoning": [
        "Good color saturation",
        "Typical coin surface texture",
        "Matches BICOLOR group"
      ]
    },
    {
      "coin_index": 7,
      "category": "Large",
      "is_coin": true,
      "confidence": 0.85,
      "color_group": "BICOLOR",
      "circle": {
        "x": 190,
        "y": 127,
        "r": 92
      },
      "reasoning": [
        "Good color saturation",
        "Typical coin surface texture",
        "Matches BICOLOR group"
      ]
    },
    {
      "coin_index": 8,
      "category": "Large",
      "is_coin": true,
      "confidence": 0.85,
      "color_group": "BICOLOR",
      "circle": {
        "x": 259,
        "y": 240,
        "r": 91
      },
      "reasoning": [
        "Good color saturation",
        "Typical coin surface texture",
        "Matches BICOLOR group"
      ]
    },
    {
      "coin_index": 9,
      "category": "Large",
      "is_coin": true,
      "confidence": 0.85,
      "color_group": "BICOLOR",
      "circle": {
        "x": 385,
        "y": 130,
        "r": 88
      },
      "reasoning": [
        "Good color saturation",
        "Typical coin surface texture",
        "Matches BICOLOR group"
      ]
    },
    {
      "coin_index": 10,
      "category": "Large",
      "is_coin": true,
      "confidence": 0.85,
      "color_group": "GOLD",
      "circle": {
        "x": 519,
        "y": 366,
        "r": 87
      },
      "reasoning": [
        "Good color saturation",
        "Typical coin surface texture",
        "Matches GOLD group"
      ]
    },
    {
      "coin_index": 11,
      "category": "Large",
      "is_coin": true,
      "confidence": 0.85,
      "color_group": "BICOLOR",
      "circle": {
        "x": 469,
        "y": 109,
        "r": 85
      },
      "reasoning": [
        "Good color saturation",
        "Typical coin surface texture",
        "Matches BICOLOR group"
      ]
    },
    {
      "coin_index": 12,
      "category": "Large",
      "is_coin": true,
      "confidence": 0.85,
      "color_group": "BICOLOR",
      "circle": {
        "x": 139,
        "y": 421,
        "r": 85
      },
      "reasoning": [
        "Good color saturation",
        "Typical coin surface texture",
        "Matches BICOLOR group"
      ]
    },
    {
      "coin_index": 13,
      "category": "Large",
      "is_coin": true,
      "confidence": 0.85,
      "color_group": "BICOLOR",
      "circle": {
        "x": 493,
        "y": 273,
        "r": 76
      },
      "reasoning": [
        "Good color saturation",
        "Typical coin surface texture",
        "Matches BICOLOR group"
      ]
    },
    {
      "coin_index": 14,
      "category": "Large",
      "is_coin": true,
      "confidence": 0.85,
      "color_group": "GOLD",
      "circle": {
        "x": 405,
        "y": 485,
        "r": 72
      },
      "reasoning": [
        "Good color saturation",
        "Typical coin surface texture",
        "Matches GOLD group"
      ]
    },
    {
      "coin_index": 15,
      "category": "Large",
      "is_coin": true,
      "confidence": 0.85,
      "color_group": "GOLD",
      "circle": {
        "x": 81,
        "y": 172,
        "r": 64
      },
      "reasoning": [
        "Good color saturation",
        "Typical coin surface texture",
        "Matches GOLD group"
      ]
    },
    {
      "coin_index": 16,
      "category": "Large",
      "is_coin": true,
      "confidence": 0.85,
      "color_group": "BICOLOR",
      "circle": {
        "x": 575,
        "y": 262,
        "r": 64
      },
      "reasoning": [
        "Good color saturation",
        "Typical coin surface texture",
        "Matches BICOLOR group"
      ]
    },
    {
      "coin_index": 17,
      "category": "Large",
      "is_coin": true,
      "confidence": 0.5,
      "color_group": "GOLD",
      "circle": {
        "x": 499,
        "y": 425,
        "r": 63
      },
      "reasoning": [
        "Good color saturation",
        "Surface too uniform (likely noise)",
        "Matches GOLD group"
      ]
    },
    {
      "coin_index": 18,
      "category": "Large",
      "is_coin": true,
      "confidence": 0.85,
      "color_group": "BICOLOR",
      "circle": {
        "x": 99,
        "y": 364,
        "r": 63
      },
      "reasoning": [
        "Good color saturation",
        "Typical coin surface texture",
        "Matches BICOLOR group"
      ]
    },
    {
      "coin_index": 19,
      "category": "Large",
      "is_coin": true,
      "confidence": 0.5,
      "color_group": "GOLD",
      "circle": {
        "x": 334,
        "y": 307,
        "r": 56
      },
      "reasoning": [
        "Good color saturation",
        "Surface too uniform (likely noise)",
        "Matches GOLD group"
      ]
    },
    {
      "coin_index": 20,
      "category": "Large",
      "is_coin": true,
      "confidence": 0.85,
      "color_group": "BICOLOR",
      "circle": {
        "x": 264,
        "y": 43,
        "r": 56
      },
      "reasoning": [
        "Good color saturation",
        "Typical coin surface texture",
        "Matches BICOLOR group"
      ]
    },
    {
      "coin_index": 21,
      "category": "Large",
      "is_coin": true,
      "confidence": 0.7,
      "color_group": "GOLD",
      "circle": {
        "x": 87,
        "y": 89,
        "r": 55
      },
      "reasoning": [
        "Good color saturation",
        "Matches GOLD group"
      ]
    },
    {
      "coin_index": 22,
      "category": "Large",
      "is_coin": true,
      "confidence": 0.85,
      "color_group": "BICOLOR",
      "circle": {
        "x": 190,
        "y": 381,
        "r": 55
      },
      "reasoning": [
        "Good color saturation",
        "Typical coin surface texture",
        "Matches BICOLOR group"
      ]
    },
    {
      "coin_index": 23,
      "category": "Large",
      "is_coin": true,
      "confidence": 0.85,
      "color_group": "BICOLOR",
      "circle": {
        "x": 312,
        "y": 463,
        "r": 55
      },
      "reasoning": [
        "Good color saturation",
        "Typical coin surface texture",
        "Matches BICOLOR group"
      ]
    },
    {
      "coin_index": 24,
      "category": "Large",
      "is_coin": true,
      "confidence": 0.85,
      "color_group": "BICOLOR",
      "circle": {
        "x": 49,
        "y": 252,
        "r": 55
      },
      "reasoning": [
        "Good color saturation",
        "Typical coin surface texture",
        "Matches BICOLOR group"
      ]
    },
    {
      "coin_index": 25,
      "category": "Large",
      "is_coin": true,
      "confidence": 0.5,
      "color_group": "GOLD",
      "circle": {
        "x": 365,
        "y": 437,
        "r": 54
      },
      "reasoning": [
        "Good color saturation",
        "Surface too uniform (likely noise)",
        "Matches GOLD group"
      ]
    },
    {
      "coin_index": 26,
      "category": "Large",
      "is_coin": true,
      "confidence": 0.85,
      "color_group": "BICOLOR",
      "circle": {
        "x": 370,
        "y": 59,
        "r": 52
      },
      "reasoning": [
        "Good color saturation",
        "Typical coin surface texture",
        "Matches BICOLOR group"
      ]
    },
    {
      "coin_index": 27,
      "category": "Large",
      "is_coin": true,
      "confidence": 0.85,
      "color_group": "BICOLOR",
      "circle": {
        "x": 547,
        "y": 117,
        "r": 51
      },
      "reasoning": [
        "Good color saturation",
        "Typical coin surface texture",
        "Matches BICOLOR group"
      ]
    },
    {
      "coin_index": 28,
      "category": "Large",
      "is_coin": true,
      "confidence": 0.5,
      "color_group": "GOLD",
      "circle": {
        "x": 420,
        "y": 186,
        "r": 50
      },
      "reasoning": [
        "Good color saturation",
        "Surface too uniform (likely noise)",
        "Matches GOLD group"
      ]
    },
    {
      "coin_index": 29,
      "category": "Large",
      "is_coin": true,
      "confidence": 0.5,
      "color_group": "GOLD",
      "circle": {
        "x": 201,
        "y": 304,
        "r": 49
      },
      "reasoning": [
        "Good color saturation",
        "Surface too uniform (likely noise)",
        "Matches GOLD group"
      ]
    },
    {
      "coin_index": 30,
      "category": "Large",
      "is_coin": true,
      "confidence": 0.5,
      "color_group": "GOLD",
      "circle": {
        "x": 303,
        "y": 186,
        "r": 49
      },
      "reasoning": [
        "Good color saturation",
        "Surface too uniform (likely noise)",
        "Matches GOLD group"
      ]
    },
    {
      "coin_index": 31,
      "category": "Large",
      "is_coin": true,
      "confidence": 0.5,
      "color_group": "GOLD",
      "circle": {
        "x": 186,
        "y": 184,
        "r": 49
      },
      "reasoning": [
        "Good color saturation",
        "Surface too uniform (likely noise)",
        "Matches GOLD group"
      ]
    },
    {
      "coin_index": 32,
      "category": "Large",
      "is_coin": true,
      "confidence": 0.5,
      "color_group": "GOLD",
      "circle": {
        "x": 533,
        "y": 190,
        "r": 48
      },
      "reasoning": [
        "Good color saturation",
        "Surface too uniform (likely noise)",
        "Matches GOLD group"
      ]
    },
    {
      "coin_index": 33,
      "category": "Large",
      "is_coin": true,
      "confidence": 0.85,
      "color_group": "BICOLOR",
      "circle": {
        "x": 415,
        "y": 431,
        "r": 48
      },
      "reasoning": [
        "Good color saturation",
        "Typical coin surface texture",
        "Matches BICOLOR group"
      ]
    },
    {
      "coin_index": 34,
      "category": "Large",
      "is_coin": true,
      "confidence": 0.7,
      "color_group": "GOLD",
      "circle": {
        "x": 424,
        "y": 77,
        "r": 46
      },
      "reasoning": [
        "Good color saturation",
        "Matches GOLD group"
      ]
    },
    {
      "coin_index": 35,
      "category": "Large",
      "is_coin": true,
      "confidence": 0.85,
      "color_group": "BICOLOR",
      "circle": {
        "x": 339,
        "y": 382,
        "r": 46
      },
      "reasoning": [
        "Good color saturation",
        "Typical coin surface texture",
        "Matches BICOLOR group"
      ]
    },
    {
      "coin_index": 36,
      "category": "Medium",
      "is_coin": true,
      "confidence": 0.5,
      "color_group": "GOLD",
      "circle": {
        "x": 210,
        "y": 75,
        "r": 44
      },
      "reasoning": [
        "Good color saturation",
        "Surface too uniform (likely noise)",
        "Matches GOLD group"
      ]
    },
    {
      "coin_index": 37,
      "category": "Medium",
      "is_coin": true,
      "confidence": 0.5,
      "color_group": "GOLD",
      "circle": {
        "x": 75,
        "y": 311,
        "r": 42
      },
      "reasoning": [
        "Good color saturation",
        "Surface too uniform (likely noise)",
        "Matches GOLD group"
      ]
    },
    {
      "coin_index": 38,
      "category": "Medium",
      "is_coin": true,
      "confidence": 0.85,
      "color_group": "BICOLOR",
      "circle": {
        "x": 34,
        "y": 90,
        "r": 42
      },
      "reasoning": [
        "Good color saturation",
        "Typical coin surface texture",
        "Matches BICOLOR group"
      ]
    },
    {
      "coin_index": 39,
      "category": "Medium",
      "is_coin": true,
      "confidence": 0.7,
      "color_group": "GOLD",
      "circle": {
        "x": 453,
        "y": 293,
        "r": 40
      },
      "reasoning": [
        "Good color saturation",
        "Matches GOLD group"
      ]
    },
    {
      "coin_index": 40,
      "category": "Medium",
      "is_coin": true,
      "confidence": 0.7,
      "color_group": "GOLD",
      "circle": {
        "x": 229,
        "y": 433,
        "r": 40
      },
      "reasoning": [
        "Good color saturation",
        "Matches GOLD group"
      ]
    },
    {
      "coin_index": 41,
      "category": "Medium",
      "is_coin": true,
      "confidence": 0.5,
      "color_group": "GOLD",
      "circle": {
        "x": 541,
        "y": 293,
        "r": 40
      },
      "reasoning": [
        "Good color saturation",
        "Surface too uniform (likely noise)",
        "Matches GOLD group"
      ]
    },
    {
      "coin_index": 42,
      "category": "Medium",
      "is_coin": true,
      "confidence": 0.5,
      "color_group": "GOLD",
      "circle": {
        "x": 317,
        "y": 72,
        "r": 40
      },
      "reasoning": [
        "Good color saturation",
        "Surface too uniform (likely noise)",
        "Matches GOLD group"
      ]
    },
    {
      "coin_index": 43,
      "category": "Medium",
      "is_coin": true,
      "confidence": 0.85,
      "color_group": "BICOLOR",
      "circle": {
        "x": 143,
        "y": 174,
        "r": 40
      },
      "reasoning": [
        "Good color saturation",
        "Typical coin surface texture",
        "Matches BICOLOR group"
      ]
    },
    {
      "coin_index": 44,
      "category": "Medium",
      "is_coin": true,
      "confidence": 0.85,
      "color_group": "BICOLOR",
      "circle": {
        "x": 114,
        "y": 199,
        "r": 36
      },
      "reasoning": [
        "Good color saturation",
        "Typical coin surface texture",
        "Matches BICOLOR group"
      ]
    },
    {
      "coin_index": 45,
      "category": "Medium",
      "is_coin": true,
      "confidence": 0.85,
      "color_group": "BICOLOR",
      "circle": {
        "x": 37,
        "y": 216,
        "r": 36
      },
      "reasoning": [
        "Good color saturation",
        "Typical coin surface texture",
        "Matches BICOLOR group"
      ]
    },
    {
      "coin_index": 46,
      "category": "Medium",
      "is_coin": true,
      "confidence": 0.85,
      "color_group": "BICOLOR",
      "circle": {
        "x": 73,
        "y": 345,
        "r": 35
      },
      "reasoning": [
        "Good color saturation",
        "Typical coin surface texture",
        "Matches BICOLOR group"
      ]
    },
    {
      "coin_index": 47,
      "category": "Medium",
      "is_coin": true,
      "confidence": 0.5,
      "color_group": "GOLD",
      "circle": {
        "x": 96,
        "y": 462,
        "r": 34
      },
      "reasoning": [
        "Good color saturation",
        "Surface too uniform (likely noise)",
        "Matches GOLD group"
      ]
    },
    {
      "coin_index": 48,
      "category": "Medium",
      "is_coin": true,
      "confidence": 0.85,
      "color_group": "GOLD",
      "circle": {
        "x": 504,
        "y": 65,
        "r": 34
      },
      "reasoning": [
        "Good color saturation",
        "Typical coin surface texture",
        "Matches GOLD group"
      ]
    },
    {
      "coin_index": 49,
      "category": "Medium",
      "is_coin": true,
      "confidence": 0.7,
      "color_group": "GOLD",
      "circle": {
        "x": 526,
        "y": 451,
        "r": 31
      },
      "reasoning": [
        "Good color saturation",
        "Matches GOLD group"
      ]
    },
    {
      "coin_index": 50,
      "category": "Medium",
      "is_coin": true,
      "confidence": 0.5,
      "color_group": "GOLD",
      "circle": {
        "x": 365,
        "y": 407,
        "r": 31
      },
      "reasoning": [
        "Good color saturation",
        "Surface too uniform (likely noise)",
        "Matches GOLD group"
      ]
    },
    {
      "coin_index": 51,
      "category": "Medium",
      "is_coin": true,
      "confidence": 0.5,
      "color_group": "GOLD",
      "circle": {
        "x": 71,
        "y": 407,
        "r": 31
      },
      "reasoning": [
        "Good color saturation",
        "Surface too uniform (likely noise)",
        "Matches GOLD group"
      ]
    },
    {
      "coin_index": 52,
      "category": "Medium",
      "is_coin": true,
      "confidence": 0.7,
      "color_group": "GOLD",
      "circle": {
        "x": 257,
        "y": 421,
        "r": 31
      },
      "reasoning": [
        "Good color saturation",
        "Matches GOLD group"
      ]
    },
    {
      "coin_index": 53,
      "category": "Medium",
      "is_coin": true,
      "confidence": 0.5,
      "color_group": "GOLD",
      "circle": {
        "x": 64,
        "y": 451,
        "r": 31
      },
      "reasoning": [
        "Good color saturation",
        "Surface too uniform (likely noise)",
        "Matches GOLD group"
      ]
    },
    {
      "coin_index": 54,
      "category": "Medium",
      "is_coin": true,
      "confidence": 0.85,
      "color_group": "BICOLOR",
      "circle": {
        "x": 156,
        "y": 76,
        "r": 31
      },
      "reasoning": [
        "Good color saturation",
        "Typical coin surface texture",
        "Matches BICOLOR group"
      ]
    },
    {
      "coin_index": 55,
      "category": "Medium",
      "is_coin": true,
      "confidence": 0.5,
      "color_group": "GOLD",
      "circle": {
        "x": 199,
        "y": 423,
        "r": 30
      },
      "reasoning": [
        "Good color saturation",
        "Surface too uniform (likely noise)",
        "Matches GOLD group"
      ]
    },
    {
      "coin_index": 56,
      "category": "Medium",
      "is_coin": true,
      "confidence": 0.5,
      "color_group": "GOLD",
      "circle": {
        "x": 348,
        "y": 465,
        "r": 29
      },
      "reasoning": [
        "Good color saturation",
        "Surface too uniform (likely noise)",
        "Matches GOLD group"
      ]
    },
    {
      "coin_index": 57,
      "category": "Medium",
      "is_coin": true,
      "confidence": 0.7,
      "color_group": "GOLD",
      "circle": {
        "x": 378,
        "y": 467,
        "r": 29
      },
      "reasoning": [
        "Good color saturation",
        "Matches GOLD group"
      ]
    },
    {
      "coin_index": 58,
      "category": "Medium",
      "is_coin": true,
      "confidence": 0.7,
      "color_group": "GOLD",
      "circle": {
        "x": 222,
        "y": 401,
        "r": 29
      },
      "reasoning": [
        "Good color saturation",
        "Matches GOLD group"
      ]
    },
    {
      "coin_index": 59,
      "category": "Small",
      "is_coin": true,
      "confidence": 0.5,
      "color_group": "GOLD",
      "circle": {
        "x": 69,
        "y": 61,
        "r": 28
      },
      "reasoning": [
        "Good color saturation",
        "Surface too uniform (likely noise)",
        "Matches GOLD group"
      ]
    },
    {
      "coin_index": 60,
      "category": "Small",
      "is_coin": true,
      "confidence": 0.5,
      "color_group": "GOLD",
      "circle": {
        "x": 245,
        "y": 463,
        "r": 28
      },
      "reasoning": [
        "Good color saturation",
        "Surface too uniform (likely noise)",
        "Matches GOLD group"
      ]
    },
    {
      "coin_index": 61,
      "category": "Small",
      "is_coin": true,
      "confidence": 0.85,
      "color_group": "BICOLOR",
      "circle": {
        "x": 541,
        "y": 41,
        "r": 28
      },
      "reasoning": [
        "Good color saturation",
        "Typical coin surface texture",
        "Matches BICOLOR group"
      ]
    },
    {
      "coin_index": 62,
      "category": "Small",
      "is_coin": true,
      "confidence": 0.85,
      "color_group": "BICOLOR",
      "circle": {
        "x": 105,
        "y": 33,
        "r": 28
      },
      "reasoning": [
        "Good color saturation",
        "Typical coin surface texture",
        "Matches BICOLOR group"
      ]
    },
    {
      "coin_index": 63,
      "category": "Small",
      "is_coin": true,
      "confidence": 0.7,
      "color_group": "GOLD",
      "circle": {
        "x": 60,
        "y": 109,
        "r": 27
      },
      "reasoning": [
        "Good color saturation",
        "Matches GOLD group"
      ]
    },
    {
      "coin_index": 64,
      "category": "Small",
      "is_coin": true,
      "confidence": 0.5,
      "color_group": "GOLD",
      "circle": {
        "x": 310,
        "y": 328,
        "r": 27
      },
      "reasoning": [
        "Good color saturation",
        "Surface too uniform (likely noise)",
        "Matches GOLD group"
      ]
    },
    {
      "coin_index": 65,
      "category": "Small",
      "is_coin": true,
      "confidence": 0.5,
      "color_group": "GOLD",
      "circle": {
        "x": 124,
        "y": 449,
        "r": 26
      },
      "reasoning": [
        "Good color saturation",
        "Surface too uniform (likely noise)",
        "Matches GOLD group"
      ]
    },
    {
      "coin_index": 66,
      "category": "Small",
      "is_coin": true,
      "confidence": 0.7,
      "color_group": "GOLD",
      "circle": {
        "x": 108,
        "y": 406,
        "r": 25
      },
      "reasoning": [
        "Good color saturation",
        "Matches GOLD group"
      ]
    },
    {
      "coin_index": 67,
      "category": "Small",
      "is_coin": true,
      "confidence": 0.5,
      "color_group": "GOLD",
      "circle": {
        "x": 171,
        "y": 310,
        "r": 25
      },
      "reasoning": [
        "Good color saturation",
        "Surface too uniform (likely noise)",
        "Matches GOLD group"
      ]
    },
    {
      "coin_index": 68,
      "category": "Small",
      "is_coin": true,
      "confidence": 0.7,
      "color_group": "GOLD",
      "circle": {
        "x": 552,
        "y": 437,
        "r": 24
      },
      "reasoning": [
        "Good color saturation",
        "Matches GOLD group"
      ]
    },
    {
      "coin_index": 69,
      "category": "Small",
      "is_coin": true,
      "confidence": 0.85,
      "color_group": "GOLD",
      "circle": {
        "x": 511,
        "y": 299,
        "r": 23
      },
      "reasoning": [
        "Good color saturation",
        "Typical coin surface texture",
        "Matches GOLD group"
      ]
    },
    {
      "coin_index": 70,
      "category": "Small",
      "is_coin": true,
      "confidence": 0.85,
      "color_group": "GOLD",
      "circle": {
        "x": 551,
        "y": 469,
        "r": 22
      },
      "reasoning": [
        "Good color saturation",
        "Typical coin surface texture",
        "Matches GOLD group"
      ]
    },
    {
      "coin_index": 71,
      "category": "Small",
      "is_coin": true,
      "confidence": 0.5,
      "color_group": "GOLD",
      "circle": {
        "x": 563,
        "y": 184,
        "r": 21
      },
      "reasoning": [
        "Good color saturation",
        "Surface too uniform (likely noise)",
        "Matches GOLD group"
      ]
    },
    {
      "coin_index": 72,
      "category": "Small",
      "is_coin": true,
      "confidence": 0.7,
      "color_group": "GOLD",
      "circle": {
        "x": 231,
        "y": 299,
        "r": 21
      },
      "reasoning": [
        "Good color saturation",
        "Matches GOLD group"
      ]
    },
    {
      "coin_index": 73,
      "category": "Small",
      "is_coin": true,
      "confidence": 0.85,
      "color_group": "BICOLOR",
      "circle": {
        "x": 483,
        "y": 485,
        "r": 21
      },
      "reasoning": [
        "Good color saturation",
        "Typical coin surface texture",
        "Matches BICOLOR group"
      ]
    },
    {
      "coin_index": 74,
      "category": "Small",
      "is_coin": true,
      "confidence": 0.85,
      "color_group": "GOLD",
      "circle": {
        "x": 208,
        "y": 489,
        "r": 19
      },
      "reasoning": [
        "Good color saturation",
        "Typical coin surface texture",
        "Matches GOLD group"
      ]
    },
    {
      "coin_index": 75,
      "category": "Small",
      "is_coin": true,
      "confidence": 0.5,
      "color_group": "GOLD",
      "circle": {
        "x": 172,
        "y": 156,
        "r": 18
      },
      "reasoning": [
        "Good color saturation",
        "Surface too uniform (likely noise)",
        "Matches GOLD group"
      ]
    },
    {
      "coin_index": 76,
      "category": "Small",
      "is_coin": true,
      "confidence": 0.7,
      "color_group": "GOLD",
      "circle": {
        "x": 519,
        "y": 216,
        "r": 18
      },
      "reasoning": [
        "Good color saturation",
        "Matches GOLD group"
      ]
    },
    {
      "coin_index": 77,
      "category": "Small",
      "is_coin": true,
      "confidence": 0.85,
      "color_group": "GOLD",
      "circle": {
        "x": 556,
        "y": 319,
        "r": 18
      },
      "reasoning": [
        "Good color saturation",
        "Typical coin surface texture",
        "Matches GOLD group"
      ]
    },
    {
      "coin_index": 78,
      "category": "Small",
      "is_coin": true,
      "confidence": 0.7,
      "color_group": "GOLD",
      "circle": {
        "x": 567,
        "y": 75,
        "r": 17
      },
      "reasoning": [
        "Good color saturation",
        "Matches GOLD group"
      ]
    },
    {
      "coin_index": 79,
      "category": "Small",
      "is_coin": true,
      "confidence": 0.7,
      "color_group": "COPPER",
      "circle": {
        "x": 85,
        "y": 239,
        "r": 17
      },
      "reasoning": [
        "Good color saturation",
        "Matches COPPER group"
      ]
    },
    {
      "coin_index": 80,
      "category": "Small",
      "is_coin": true,
      "confidence": 0.5,
      "color_group": "GOLD",
      "circle": {
        "x": 444,
        "y": 54,
        "r": 17
      },
      "reasoning": [
        "Good color saturation",
        "Surface too uniform (likely noise)",
        "Matches GOLD group"
      ]
    },
    {
      "coin_index": 81,
      "category": "Small",
      "is_coin": true,
      "confidence": 0.5,
      "color_group": "GOLD",
      "circle": {
        "x": 46,
        "y": 324,
        "r": 17
      },
      "reasoning": [
        "Good color saturation",
        "Surface too uniform (likely noise)",
        "Matches GOLD group"
      ]
    },
    {
      "coin_index": 82,
      "category": "Small",
      "is_coin": true,
      "confidence": 0.7,
      "color_group": "COPPER",
      "circle": {
        "x": 411,
        "y": 49,
        "r": 16
      },
      "reasoning": [
        "Good color saturation",
        "Matches COPPER group"
      ]
    },
    {
      "coin_index": 83,
      "category": "Small",
      "is_coin": true,
      "confidence": 0.5,
      "color_group": "GOLD",
      "circle": {
        "x": 569,
        "y": 412,
        "r": 16
      },
      "reasoning": [
        "Good color saturation",
        "Surface too uniform (likely noise)",
        "Matches GOLD group"
      ]
    },
    {
      "coin_index": 84,
      "category": "Small",
      "is_coin": true,
      "confidence": 0.5,
      "color_group": "GOLD",
      "circle": {
        "x": 293,
        "y": 53,
        "r": 15
      },
      "reasoning": [
        "Good color saturation",
        "Surface too uniform (likely noise)",
        "Matches GOLD group"
      ]
    },
    {
      "coin_index": 85,
      "category": "Small",
      "is_coin": true,
      "confidence": 0.7,
      "color_group": "GOLD",
      "circle": {
        "x": 436,
        "y": 107,
        "r": 15
      },
      "reasoning": [
        "Good color saturation",
        "Matches GOLD group"
      ]
    }
  ]
}